TextLabeling/__init__.py
TextLabeling/_comm_api.py
TextLabeling/_data_preprocessing.py
TextLabeling/_demodata.py
text_labeling-0.1.2.dist-info/LICENSE
text_labeling-0.1.2.dist-info/METADATA
text_labeling-0.1.2.dist-info/WHEEL
text_labeling-0.1.2.dist-info/top_level.txt
text_labeling-0.1.2.dist-info/RECORD
