Metadata-Version: 2.1
Name: text-labeling
Version: 0.1.2
Summary: Visual Text Labeling tool.
Home-page: https://github.com/soniacq/TextLabelingTool
Author: Sonia Castelo
Author-email: s.castelo@nyu.edu
License: UNKNOWN
Platform: UNKNOWN
Classifier: Programming Language :: Python :: 3
Classifier: License :: OSI Approved :: BSD License
Classifier: Operating System :: OS Independent
Requires-Python: >=3.6
Requires-Dist: python-dateutil
Requires-Dist: numpy
Requires-Dist: scipy
Requires-Dist: scikit-learn
Requires-Dist: notebook
Requires-Dist: pandas
Requires-Dist: nltk
Requires-Dist: spacy
Requires-Dist: modAL
